{
  "generatedAt": "2026-03-21T17:37:44.753Z",
  "beats": {
    "totalEntries": 404,
    "uniqueBeatKeys": 315,
    "byLayer": {
      "L1": 216,
      "L2": 188,
      "other": 0
    },
    "firstBeatKey": "0:0:0:0",
    "lastBeatKey": "2:3:1:10",
    "firstTimeMs": 0,
    "lastTimeMs": 51984.55139631611,
    "spanMs": 51984.551
  },
  "regimes": {
    "initializing": 4,
    "evolving": 4,
    "coherent": 82,
    "exploring": 314
  },
  "regimeDepth": {
    "maxConsecutiveCoherent": 82,
    "transitionCount": 3
  },
  "conductor": {
    "playProb": {
      "min": 0.23897465222206235,
      "max": 0.49853494399628234,
      "avg": 0.3804,
      "count": 404
    },
    "stutterProb": {
      "min": 0.22859125,
      "max": 0.8441840443216011,
      "avg": 0.4412,
      "count": 404
    },
    "density": {
      "min": 0.31548652935454335,
      "max": 0.6570577935873407,
      "avg": 0.505,
      "count": 404
    },
    "tension": {
      "min": 0.05282990339917208,
      "max": 0.8545084772312908,
      "avg": 0.5792,
      "count": 404
    },
    "flicker": {
      "min": 0.799090349027886,
      "max": 1.101127457318893,
      "avg": 0.9145,
      "count": 404
    }
  },
  "couplingAbs": {
    "density-entropy": {
      "min": 0.005,
      "max": 1,
      "avg": 0.2611,
      "count": 400
    },
    "density-flicker": {
      "min": 0.008,
      "max": 0.999,
      "avg": 0.3764,
      "count": 400
    },
    "density-phase": {
      "min": 0,
      "max": 0.653,
      "avg": 0.049,
      "count": 400
    },
    "density-tension": {
      "min": 0.004,
      "max": 0.999,
      "avg": 0.3623,
      "count": 400
    },
    "density-trust": {
      "min": 0,
      "max": 0.971,
      "avg": 0.3248,
      "count": 400
    },
    "entropy-phase": {
      "min": 0,
      "max": 0.596,
      "avg": 0.0349,
      "count": 400
    },
    "entropy-trust": {
      "min": 0,
      "max": 0.971,
      "avg": 0.2752,
      "count": 400
    },
    "flicker-entropy": {
      "min": 0.013,
      "max": 0.998,
      "avg": 0.2719,
      "count": 400
    },
    "flicker-phase": {
      "min": 0,
      "max": 0.592,
      "avg": 0.0448,
      "count": 400
    },
    "flicker-trust": {
      "min": 0,
      "max": 0.98,
      "avg": 0.4201,
      "count": 400
    },
    "tension-entropy": {
      "min": 0.02,
      "max": 0.999,
      "avg": 0.3118,
      "count": 400
    },
    "tension-flicker": {
      "min": 0.002,
      "max": 1,
      "avg": 0.2344,
      "count": 400
    },
    "tension-phase": {
      "min": 0,
      "max": 0.608,
      "avg": 0.0538,
      "count": 400
    },
    "tension-trust": {
      "min": 0,
      "max": 0.977,
      "avg": 0.3179,
      "count": 400
    }
  },
  "couplingTail": {
    "density-entropy": {
      "p90": 0.635,
      "p95": 0.65,
      "exceedanceRate": {
        "0.50": 0.17,
        "0.70": 0.0375,
        "0.85": 0.01
      }
    },
    "density-flicker": {
      "p90": 0.883,
      "p95": 0.9501,
      "exceedanceRate": {
        "0.50": 0.225,
        "0.70": 0.1975,
        "0.85": 0.19
      }
    },
    "density-phase": {
      "p90": 0.195,
      "p95": 0.287,
      "exceedanceRate": {
        "0.50": 0.035,
        "0.70": 0,
        "0.85": 0
      }
    },
    "density-tension": {
      "p90": 0.564,
      "p95": 0.7383,
      "exceedanceRate": {
        "0.50": 0.13,
        "0.70": 0.0675,
        "0.85": 0.0425
      }
    },
    "density-trust": {
      "p90": 0.767,
      "p95": 0.77,
      "exceedanceRate": {
        "0.50": 0.2625,
        "0.70": 0.1375,
        "0.85": 0.0075
      }
    },
    "entropy-phase": {
      "p90": 0.1166,
      "p95": 0.269,
      "exceedanceRate": {
        "0.50": 0.005,
        "0.70": 0,
        "0.85": 0
      }
    },
    "entropy-trust": {
      "p90": 0.574,
      "p95": 0.643,
      "exceedanceRate": {
        "0.50": 0.18,
        "0.70": 0.01,
        "0.85": 0.005
      }
    },
    "flicker-entropy": {
      "p90": 0.515,
      "p95": 0.5471,
      "exceedanceRate": {
        "0.50": 0.1375,
        "0.70": 0.0125,
        "0.85": 0.01
      }
    },
    "flicker-phase": {
      "p90": 0.2019,
      "p95": 0.3013,
      "exceedanceRate": {
        "0.50": 0.0175,
        "0.70": 0,
        "0.85": 0
      }
    },
    "flicker-trust": {
      "p90": 0.743,
      "p95": 0.824,
      "exceedanceRate": {
        "0.50": 0.4275,
        "0.70": 0.145,
        "0.85": 0.0075
      }
    },
    "tension-entropy": {
      "p90": 0.6192,
      "p95": 0.6914,
      "exceedanceRate": {
        "0.50": 0.2025,
        "0.70": 0.0475,
        "0.85": 0.01
      }
    },
    "tension-flicker": {
      "p90": 0.514,
      "p95": 0.7003,
      "exceedanceRate": {
        "0.50": 0.125,
        "0.70": 0.0525,
        "0.85": 0.04
      }
    },
    "tension-phase": {
      "p90": 0.221,
      "p95": 0.4689,
      "exceedanceRate": {
        "0.50": 0.045,
        "0.70": 0,
        "0.85": 0
      }
    },
    "tension-trust": {
      "p90": 0.617,
      "p95": 0.649,
      "exceedanceRate": {
        "0.50": 0.2025,
        "0.70": 0.025,
        "0.85": 0.0075
      }
    }
  },
  "couplingHotspots": [
    {
      "pair": "density-flicker",
      "p95": 0.9501,
      "avg": 0.3764
    },
    {
      "pair": "density-tension",
      "p95": 0.7383,
      "avg": 0.3623
    },
    {
      "pair": "density-trust",
      "p95": 0.77,
      "avg": 0.3248
    },
    {
      "pair": "flicker-trust",
      "p95": 0.824,
      "avg": 0.4201
    },
    {
      "pair": "tension-flicker",
      "p95": 0.7003,
      "avg": 0.2344
    }
  ],
  "couplingCorrelation": {
    "density-entropy": {
      "pearsonR": 0.1956,
      "meanSigned": -0.0135,
      "direction": "stable"
    },
    "density-flicker": {
      "pearsonR": -0.7857,
      "meanSigned": 0.147,
      "direction": "decreasing"
    },
    "density-phase": {
      "pearsonR": -0.1975,
      "meanSigned": 0.0336,
      "direction": "stable"
    },
    "density-tension": {
      "pearsonR": 0.233,
      "meanSigned": 0.0404,
      "direction": "stable"
    },
    "density-trust": {
      "pearsonR": 0.3383,
      "meanSigned": -0.2331,
      "direction": "increasing"
    },
    "entropy-phase": {
      "pearsonR": 0.0437,
      "meanSigned": -0.0084,
      "direction": "stable"
    },
    "entropy-trust": {
      "pearsonR": -0.225,
      "meanSigned": 0.1317,
      "direction": "stable"
    },
    "flicker-entropy": {
      "pearsonR": 0.1702,
      "meanSigned": 0.0852,
      "direction": "stable"
    },
    "flicker-phase": {
      "pearsonR": 0.083,
      "meanSigned": 0.0007,
      "direction": "stable"
    },
    "flicker-trust": {
      "pearsonR": 0.5786,
      "meanSigned": -0.0229,
      "direction": "increasing"
    },
    "tension-entropy": {
      "pearsonR": -0.4893,
      "meanSigned": -0.1849,
      "direction": "decreasing"
    },
    "tension-flicker": {
      "pearsonR": -0.1578,
      "meanSigned": 0.0778,
      "direction": "stable"
    },
    "tension-phase": {
      "pearsonR": 0.0671,
      "meanSigned": -0.0473,
      "direction": "stable"
    },
    "tension-trust": {
      "pearsonR": 0.4965,
      "meanSigned": 0.0622,
      "direction": "increasing"
    }
  },
  "trustScoreAbs": {
    "cadenceAlignment": {
      "min": 0.11055601693119306,
      "max": 0.238322118298988,
      "avg": 0.1805,
      "count": 404
    },
    "coherenceMonitor": {
      "min": 0.0999,
      "max": 0.6196858269329463,
      "avg": 0.5445,
      "count": 404
    },
    "convergence": {
      "min": 0.0999,
      "max": 0.26344606100171464,
      "avg": 0.2062,
      "count": 404
    },
    "entropyRegulator": {
      "min": 0.0999,
      "max": 0.5865382159457131,
      "avg": 0.2517,
      "count": 404
    },
    "feedbackOscillator": {
      "min": 0.0999,
      "max": 0.3578322728422143,
      "avg": 0.2565,
      "count": 404
    },
    "phaseLock": {
      "min": 0.0999,
      "max": 0.6241544331715881,
      "avg": 0.4654,
      "count": 404
    },
    "restSynchronizer": {
      "min": 0.15013044571730413,
      "max": 0.3917296523319023,
      "avg": 0.2397,
      "count": 404
    },
    "stutterContagion": {
      "min": 0.0999,
      "max": 0.6408059276100567,
      "avg": 0.3852,
      "count": 404
    }
  },
  "trustWeightAbs": {
    "cadenceAlignment": {
      "min": 1.054437037375,
      "max": 1.1560087284980818,
      "avg": 1.133,
      "count": 404
    },
    "coherenceMonitor": {
      "min": 1.071901,
      "max": 1.4851903355545713,
      "avg": 1.4132,
      "count": 404
    },
    "convergence": {
      "min": 1.0439949475645927,
      "max": 1.19238192869772,
      "avg": 1.1515,
      "count": 404
    },
    "entropyRegulator": {
      "min": 1.0571758828880518,
      "max": 1.426148140045722,
      "avg": 1.1642,
      "count": 404
    },
    "feedbackOscillator": {
      "min": 1.0379723989480212,
      "max": 1.2477893584400683,
      "avg": 1.1766,
      "count": 404
    },
    "phaseLock": {
      "min": 1.0634635000000001,
      "max": 1.468915081905163,
      "avg": 1.3473,
      "count": 404
    },
    "restSynchronizer": {
      "min": 1.0518823895869867,
      "max": 1.2906604096924559,
      "avg": 1.1738,
      "count": 404
    },
    "stutterContagion": {
      "min": 0.9709763119007309,
      "max": 1.4125,
      "avg": 1.2329,
      "count": 404
    }
  },
  "trustAbs": {
    "cadenceAlignment": {
      "min": 0.11055601693119306,
      "max": 0.238322118298988,
      "avg": 0.1805,
      "count": 404
    },
    "coherenceMonitor": {
      "min": 0.0999,
      "max": 0.6196858269329463,
      "avg": 0.5445,
      "count": 404
    },
    "convergence": {
      "min": 0.0999,
      "max": 0.26344606100171464,
      "avg": 0.2062,
      "count": 404
    },
    "entropyRegulator": {
      "min": 0.0999,
      "max": 0.5865382159457131,
      "avg": 0.2517,
      "count": 404
    },
    "feedbackOscillator": {
      "min": 0.0999,
      "max": 0.3578322728422143,
      "avg": 0.2565,
      "count": 404
    },
    "phaseLock": {
      "min": 0.0999,
      "max": 0.6241544331715881,
      "avg": 0.4654,
      "count": 404
    },
    "restSynchronizer": {
      "min": 0.15013044571730413,
      "max": 0.3917296523319023,
      "avg": 0.2397,
      "count": 404
    },
    "stutterContagion": {
      "min": 0.0999,
      "max": 0.6408059276100567,
      "avg": 0.3852,
      "count": 404
    }
  },
  "stageTiming": {
    "beat-setup": {
      "min": 0.614626,
      "max": 8.980444,
      "avg": 1.2469,
      "count": 404
    },
    "intent": {
      "min": 0.003482,
      "max": 0.070769,
      "avg": 0.0053,
      "count": 404
    },
    "entropy": {
      "min": 0.003862,
      "max": 0.208013,
      "avg": 0.0304,
      "count": 404
    },
    "phase": {
      "min": 0.003646,
      "max": 0.100435,
      "avg": 0.0087,
      "count": 404
    },
    "climax": {
      "min": 0.005825,
      "max": 0.096086,
      "avg": 0.012,
      "count": 404
    },
    "envelope": {
      "min": 0.003128,
      "max": 0.087794,
      "avg": 0.006,
      "count": 404
    },
    "silhouette": {
      "min": 0.004066,
      "max": 0.144663,
      "avg": 0.0065,
      "count": 404
    },
    "rest": {
      "min": 0.005283,
      "max": 0.062885,
      "avg": 0.011,
      "count": 404
    },
    "complement": {
      "min": 0.000414,
      "max": 0.020631,
      "avg": 0.0009,
      "count": 404
    },
    "tension-cadence": {
      "min": 0.00476,
      "max": 0.102771,
      "avg": 0.0183,
      "count": 404
    },
    "negotiation": {
      "min": 0.058721,
      "max": 0.949845,
      "avg": 0.2575,
      "count": 404
    },
    "probability-adjust": {
      "min": 0.000955,
      "max": 0.03165,
      "avg": 0.0044,
      "count": 404
    },
    "emission": {
      "min": 0.027002,
      "max": 3.646663,
      "avg": 0.7709,
      "count": 404
    },
    "post-beat": {
      "min": 0.00797,
      "max": 0.269657,
      "avg": 0.0178,
      "count": 404
    }
  },
  "beatSetupBudget": {
    "thresholdMs": 200,
    "exceededCount": 0,
    "totalBeats": 408,
    "exceededRate": 0,
    "spikeIndices": [],
    "worstSpike": null,
    "topSubstages": []
  },
  "adaptiveTargets": {
    "density-tension": {
      "baseline": 0.04,
      "current": 0.0395,
      "drift": -0.0005,
      "driftRatio": 0.99,
      "rollingAbsCorr": 0.2393,
      "rawRollingAbsCorr": 0.2393,
      "gain": 0.45,
      "effectiveGain": 0.1738,
      "nudgeable": true,
      "p95AbsCorr": 0.543,
      "hotspotRate": 0.0185,
      "severeRate": 0,
      "recentP95AbsCorr": 0.466,
      "recentHotspotRate": 0,
      "recentSevereRate": 0,
      "telemetryWindowBeats": 54,
      "residualPressure": 0,
      "budgetScore": 0.4844,
      "budgetBoost": 1.4,
      "budgetRank": 3,
      "heatPenalty": 0.75,
      "effectivenessEma": 0.486,
      "effMin": 0.3899,
      "effMax": 0.5993,
      "effActiveBeats": 63,
      "rawEmaMax": 0.2393
    },
    "density-flicker": {
      "baseline": 0.08,
      "current": 0.0794,
      "drift": -0.0006,
      "driftRatio": 0.99,
      "rollingAbsCorr": 0.1929,
      "rawRollingAbsCorr": 0.1929,
      "gain": 0.2582,
      "effectiveGain": 0.04,
      "nudgeable": true,
      "p95AbsCorr": 0.576,
      "hotspotRate": 0.0339,
      "severeRate": 0.0169,
      "recentP95AbsCorr": 0.576,
      "recentHotspotRate": 0,
      "recentSevereRate": 0,
      "telemetryWindowBeats": 59,
      "residualPressure": 0,
      "budgetScore": 0.8303,
      "budgetBoost": 1.8816,
      "budgetRank": 1,
      "heatPenalty": 1,
      "effectivenessEma": 0.4575,
      "effMin": 0.3434,
      "effMax": 0.5908,
      "effActiveBeats": 52,
      "rawEmaMax": 0.1929
    },
    "density-entropy": {
      "baseline": 0.04,
      "current": 0.0396,
      "drift": -0.0004,
      "driftRatio": 0.99,
      "rollingAbsCorr": 0.2196,
      "rawRollingAbsCorr": 0.2196,
      "gain": 0.4019,
      "effectiveGain": 0.1174,
      "nudgeable": true,
      "p95AbsCorr": 0.635,
      "hotspotRate": 0,
      "severeRate": 0,
      "recentP95AbsCorr": 0.367,
      "recentHotspotRate": 0,
      "recentSevereRate": 0,
      "telemetryWindowBeats": 50,
      "residualPressure": 0,
      "budgetScore": 0.322,
      "budgetBoost": 1.098,
      "budgetRank": null,
      "heatPenalty": 1,
      "effectivenessEma": 0.3707,
      "effMin": 0.3406,
      "effMax": 0.5689,
      "effActiveBeats": 55,
      "rawEmaMax": 0.2752
    },
    "density-trust": {
      "baseline": 0.04,
      "current": 0.0396,
      "drift": -0.0004,
      "driftRatio": 0.99,
      "rollingAbsCorr": 0.198,
      "rawRollingAbsCorr": 0.198,
      "gain": 0.293,
      "effectiveGain": 0,
      "nudgeable": true,
      "p95AbsCorr": 0.419,
      "hotspotRate": 0,
      "severeRate": 0,
      "recentP95AbsCorr": 0.453,
      "recentHotspotRate": 0,
      "recentSevereRate": 0,
      "telemetryWindowBeats": 48,
      "residualPressure": 0,
      "budgetScore": 0.2558,
      "budgetBoost": 1.0875,
      "budgetRank": null,
      "heatPenalty": 0.4518,
      "effectivenessEma": 0.3973,
      "effMin": 0.3086,
      "effMax": 0.5102,
      "effActiveBeats": 52,
      "rawEmaMax": 0.2131
    },
    "tension-flicker": {
      "baseline": 0.04,
      "current": 0.0359,
      "drift": -0.0041,
      "driftRatio": 0.9,
      "rollingAbsCorr": 0.1846,
      "rawRollingAbsCorr": 0.1846,
      "gain": 0.3706,
      "effectiveGain": 0.05,
      "nudgeable": true,
      "p95AbsCorr": 0.627,
      "hotspotRate": 0.0208,
      "severeRate": 0,
      "recentP95AbsCorr": 0.514,
      "recentHotspotRate": 0,
      "recentSevereRate": 0,
      "telemetryWindowBeats": 48,
      "residualPressure": 0,
      "budgetScore": 0.3391,
      "budgetBoost": 1.3216,
      "budgetRank": 5,
      "heatPenalty": 0.3,
      "effectivenessEma": 0.491,
      "effMin": 0.3676,
      "effMax": 0.5542,
      "effActiveBeats": 48,
      "rawEmaMax": 0.1846
    },
    "tension-entropy": {
      "baseline": 0.04,
      "current": 0.0373,
      "drift": -0.0027,
      "driftRatio": 0.93,
      "rollingAbsCorr": 0.2593,
      "rawRollingAbsCorr": 0.2593,
      "gain": 0.2677,
      "effectiveGain": 0.3879,
      "nudgeable": true,
      "p95AbsCorr": 0.689,
      "hotspotRate": 0.0364,
      "severeRate": 0,
      "recentP95AbsCorr": 0.309,
      "recentHotspotRate": 0,
      "recentSevereRate": 0,
      "telemetryWindowBeats": 55,
      "residualPressure": 0.0366,
      "budgetScore": 0.3394,
      "budgetBoost": 1.26,
      "budgetRank": 4,
      "heatPenalty": 0.6879,
      "effectivenessEma": 0.441,
      "effMin": 0.3559,
      "effMax": 0.51,
      "effActiveBeats": 48,
      "rawEmaMax": 0.3913
    },
    "tension-trust": {
      "baseline": 0.15547540434293072,
      "current": 0.1342,
      "drift": -0.0213,
      "driftRatio": 0.86,
      "rollingAbsCorr": 0.262,
      "rawRollingAbsCorr": 0.262,
      "gain": 0.316,
      "effectiveGain": 0.2094,
      "nudgeable": true,
      "p95AbsCorr": 0.603,
      "hotspotRate": 0,
      "severeRate": 0,
      "recentP95AbsCorr": 0.627,
      "recentHotspotRate": 0,
      "recentSevereRate": 0,
      "telemetryWindowBeats": 48,
      "residualPressure": 0,
      "budgetScore": 0.2133,
      "budgetBoost": 1.035,
      "budgetRank": null,
      "heatPenalty": 0.7654,
      "effectivenessEma": 0.4634,
      "effMin": 0.2994,
      "effMax": 0.475,
      "effActiveBeats": 53,
      "rawEmaMax": 0.2685
    },
    "flicker-entropy": {
      "baseline": 0.18022517595810067,
      "current": 0.1697,
      "drift": -0.0105,
      "driftRatio": 0.94,
      "rollingAbsCorr": 0.219,
      "rawRollingAbsCorr": 0.219,
      "gain": 0.16,
      "effectiveGain": 0,
      "nudgeable": true,
      "p95AbsCorr": 0.543,
      "hotspotRate": 0,
      "severeRate": 0,
      "recentP95AbsCorr": 0.484,
      "recentHotspotRate": 0,
      "recentSevereRate": 0,
      "telemetryWindowBeats": 48,
      "residualPressure": 0,
      "budgetScore": 0.1647,
      "budgetBoost": 1.2846,
      "budgetRank": null,
      "heatPenalty": 0.66,
      "effectivenessEma": 0.4664,
      "effMin": 0.3853,
      "effMax": 0.5482,
      "effActiveBeats": 30,
      "rawEmaMax": 0.2808
    },
    "flicker-trust": {
      "baseline": 0.04,
      "current": 0.0397,
      "drift": -0.0003,
      "driftRatio": 0.99,
      "rollingAbsCorr": 0.2671,
      "rawRollingAbsCorr": 0.2671,
      "gain": 0.45,
      "effectiveGain": 0.147,
      "nudgeable": true,
      "p95AbsCorr": 0.666,
      "hotspotRate": 0,
      "severeRate": 0,
      "recentP95AbsCorr": 0.407,
      "recentHotspotRate": 0,
      "recentSevereRate": 0,
      "telemetryWindowBeats": 56,
      "residualPressure": 0,
      "budgetScore": 0.5737,
      "budgetBoost": 1.7248,
      "budgetRank": 2,
      "heatPenalty": 1,
      "effectivenessEma": 0.4211,
      "effMin": 0.3685,
      "effMax": 0.506,
      "effActiveBeats": 58,
      "rawEmaMax": 0.2785
    },
    "entropy-trust": {
      "baseline": 0.30602416964653567,
      "current": 0.306,
      "drift": 0,
      "driftRatio": 1,
      "rollingAbsCorr": 0.1742,
      "rawRollingAbsCorr": 0.1742,
      "gain": 0,
      "effectiveGain": 0,
      "nudgeable": false,
      "p95AbsCorr": 0.644,
      "hotspotRate": 0,
      "severeRate": 0,
      "recentP95AbsCorr": 0.327,
      "recentHotspotRate": 0,
      "recentSevereRate": 0,
      "telemetryWindowBeats": 48,
      "residualPressure": 0,
      "budgetScore": 0,
      "budgetBoost": 1,
      "budgetRank": null,
      "heatPenalty": 0,
      "effectivenessEma": 0.5,
      "effMin": 1,
      "effMax": 0,
      "effActiveBeats": 0,
      "rawEmaMax": 0.2908
    },
    "flicker-phase": {
      "baseline": 0.14807407601509365,
      "current": 0.1247,
      "drift": -0.0234,
      "driftRatio": 0.84,
      "rollingAbsCorr": 0.0558,
      "rawRollingAbsCorr": 0.0558,
      "gain": 0.2648,
      "effectiveGain": 0,
      "nudgeable": true,
      "p95AbsCorr": 0.592,
      "hotspotRate": 0,
      "severeRate": 0,
      "recentP95AbsCorr": 0.592,
      "recentHotspotRate": 0,
      "recentSevereRate": 0,
      "telemetryWindowBeats": 13,
      "residualPressure": 0,
      "budgetScore": 0,
      "budgetBoost": 1,
      "budgetRank": null,
      "heatPenalty": 0.05,
      "effectivenessEma": 0.4558,
      "effMin": 0.4524,
      "effMax": 0.5012,
      "effActiveBeats": 6,
      "rawEmaMax": 0.0558
    },
    "density-phase": {
      "baseline": 0.1312418071668183,
      "current": 0.1281,
      "drift": -0.0031,
      "driftRatio": 0.98,
      "rollingAbsCorr": 0.059,
      "rawRollingAbsCorr": 0.059,
      "gain": 0.2891,
      "effectiveGain": 0.3123,
      "nudgeable": true,
      "p95AbsCorr": 0.651,
      "hotspotRate": 0,
      "severeRate": 0,
      "recentP95AbsCorr": 0.651,
      "recentHotspotRate": 0,
      "recentSevereRate": 0,
      "telemetryWindowBeats": 13,
      "residualPressure": 0,
      "budgetScore": 0,
      "budgetBoost": 1,
      "budgetRank": null,
      "heatPenalty": 0.1,
      "effectivenessEma": 0.5082,
      "effMin": 0.4287,
      "effMax": 0.5349,
      "effActiveBeats": 10,
      "rawEmaMax": 0.059
    },
    "tension-phase": {
      "baseline": 0.2426256843928327,
      "current": 0.2203,
      "drift": -0.0223,
      "driftRatio": 0.91,
      "rollingAbsCorr": 0.0679,
      "rawRollingAbsCorr": 0.0679,
      "gain": 0.16,
      "effectiveGain": 0,
      "nudgeable": true,
      "p95AbsCorr": 0.588,
      "hotspotRate": 0,
      "severeRate": 0,
      "recentP95AbsCorr": 0.588,
      "recentHotspotRate": 0,
      "recentSevereRate": 0,
      "telemetryWindowBeats": 13,
      "residualPressure": 0,
      "budgetScore": 0,
      "budgetBoost": 1,
      "budgetRank": null,
      "heatPenalty": 0,
      "effectivenessEma": 0.5,
      "effMin": 1,
      "effMax": 0,
      "effActiveBeats": 0,
      "rawEmaMax": 0.0679
    },
    "entropy-phase": {
      "baseline": 0.16362017091061387,
      "current": 0.1436,
      "drift": -0.02,
      "driftRatio": 0.88,
      "rollingAbsCorr": 0.0745,
      "rawRollingAbsCorr": 0.0745,
      "gain": 0.2117,
      "effectiveGain": 0,
      "nudgeable": true,
      "p95AbsCorr": 0.297,
      "hotspotRate": 0,
      "severeRate": 0,
      "recentP95AbsCorr": 0.297,
      "recentHotspotRate": 0,
      "recentSevereRate": 0,
      "telemetryWindowBeats": 13,
      "residualPressure": 0,
      "budgetScore": 0,
      "budgetBoost": 1,
      "budgetRank": null,
      "heatPenalty": 0.1283,
      "effectivenessEma": 0.4369,
      "effMin": 0.4073,
      "effMax": 0.475,
      "effActiveBeats": 5,
      "rawEmaMax": 0.0745
    },
    "trust-phase": {
      "baseline": 0.2942968816670022,
      "current": 0.2943,
      "drift": 0,
      "driftRatio": 1,
      "rollingAbsCorr": 0,
      "rawRollingAbsCorr": 0,
      "gain": 0,
      "effectiveGain": 0,
      "nudgeable": false,
      "p95AbsCorr": 0,
      "hotspotRate": 0,
      "severeRate": 0,
      "recentP95AbsCorr": 0,
      "recentHotspotRate": 0,
      "recentSevereRate": 0,
      "telemetryWindowBeats": 0,
      "residualPressure": 0,
      "budgetScore": 0,
      "budgetBoost": 1,
      "budgetRank": null,
      "heatPenalty": 0,
      "effectivenessEma": 0.5,
      "effMin": 1,
      "effMax": 0,
      "effActiveBeats": 0,
      "rawEmaMax": 0
    }
  },
  "axisCouplingTotals": {
    "density": 1.0344,
    "tension": 1.2571,
    "flicker": 1.0493,
    "entropy": 0.7686,
    "trust": 0.8984,
    "phase": 0.0057
  },
  "axisEnergyShare": {
    "shares": {
      "density": 0.2063,
      "tension": 0.2507,
      "flicker": 0.2093,
      "entropy": 0.1533,
      "trust": 0.1792,
      "phase": 0.0011
    },
    "axisGini": 0.2405
  },
  "couplingGates": {
    "gateD": 0.898,
    "gateT": 0.898,
    "gateF": 0.898,
    "floorDampen": 0.5022,
    "bypassD": -0.187054,
    "bypassT": 0.269499,
    "bypassF": -0.034436,
    "gateMinD": 0.3977,
    "gateMinT": 0.4653,
    "gateMinF": 0.1211,
    "gateEmaD": 0.8764,
    "gateEmaT": 0.9008,
    "gateEmaF": 0.833,
    "gateBeatCount": 64
  },
  "couplingHomeostasis": {
    "totalEnergyEma": 2.5926,
    "energyBudget": 3.2001,
    "peakEnergyEma": 2.6886,
    "totalEnergyFloor": 2.1966,
    "floorDampen": 0.5151,
    "redistributionScore": 0.9977,
    "nudgeableRedistributionScore": 0.9977,
    "budgetConstraintActive": true,
    "budgetConstraintPressure": 0.9979,
    "globalGainMultiplier": 0.6197,
    "giniCoefficient": 0.3406,
    "energyDeltaEma": -0.0277,
    "pairTurbulenceEma": 0.0836,
    "beatCount": 63,
    "invokeCount": 64,
    "tickCount": 467,
    "emptyMatrixBeats": 1,
    "multiplierMin": 0.2385,
    "multiplierMax": 1,
    "multiplierStdDev": 0.1318,
    "floorContactBeats": 5,
    "ceilingContactBeats": 6,
    "avgRecoveryDuration": 73,
    "floorRecoveryActive": true,
    "floorRecoveryTicksRemaining": 26,
    "densityFlickerTailPressure": 0.6372,
    "stickyTailPressure": 0.6508,
    "tailRecoveryDrive": 0.6169,
    "tailRecoveryTrigger": 0.2168,
    "tailRecoveryHandshake": 0.97,
    "tailRecoveryCap": 0.6198,
    "tailRecoveryCeilingPressure": 0,
    "densityFlickerClampPressure": 0.4142,
    "densityFlickerOverridePressure": 0.7478,
    "recoveryAxisHandOffPressure": 0.7356,
    "shortRunRecoveryBias": 0,
    "nonNudgeableTailPressure": 0.1214,
    "nonNudgeableTailPair": "entropy-trust",
    "recoveryDominantAxes": [
      "density",
      "flicker"
    ],
    "dominantTailPair": "density-flicker",
    "tailHotspotCount": 12,
    "tailPressureByPair": {
      "density-tension": 0.5375,
      "density-flicker": 0.6372,
      "density-entropy": 0.2585,
      "density-trust": 0.2538,
      "density-phase": 0.2094,
      "tension-flicker": 0.4528,
      "tension-entropy": 0.4318,
      "tension-trust": 0.1896,
      "tension-phase": 0.0904,
      "flicker-entropy": 0.0384,
      "flicker-trust": 0.3896,
      "flicker-phase": 0.098,
      "entropy-trust": 0.1214,
      "entropy-phase": 0,
      "trust-phase": 0
    }
  },
  "axisEnergyEquilibrator": {
    "beatCount": 64,
    "pairAdjustments": 77,
    "axisAdjustments": 66,
    "smoothedShares": {
      "density": 0.18503789052640077,
      "tension": 0.22430594177891214,
      "flicker": 0.1982590471847557,
      "entropy": 0.1598588400363025,
      "trust": 0.2161621881959177,
      "phase": 0.011117581349772747
    },
    "perAxisAdj": {
      "density": 2,
      "tension": 8,
      "flicker": 3,
      "entropy": 12,
      "trust": 3,
      "phase": 38
    },
    "perPairAdj": {
      "density-flicker": 2,
      "density-entropy": 5,
      "density-trust": 6,
      "tension-entropy": 11,
      "flicker-trust": 4,
      "density-tension": 4,
      "tension-flicker": 4,
      "tension-trust": 1,
      "tension-phase": 17,
      "flicker-phase": 3,
      "entropy-phase": 1,
      "trust-phase": 19
    },
    "lastBaselines": {
      "density-tension": 0.04,
      "density-flicker": 0.08,
      "density-entropy": 0.04,
      "tension-flicker": 0.04,
      "tension-entropy": 0.04,
      "flicker-entropy": 0.18022517595810067,
      "flicker-phase": 0.14807407601509365,
      "density-phase": 0.1312418071668183,
      "tension-phase": 0.2426256843928327,
      "density-trust": 0.04,
      "tension-trust": 0.15713687476056412,
      "flicker-trust": 0.04,
      "entropy-phase": 0.16362017091061387,
      "entropy-trust": 0.30602416964653567,
      "trust-phase": 0.2922968816670022
    },
    "regimeBeats": {
      "coherent": 3,
      "exploring": 56
    },
    "regimePairAdj": {
      "coherent": 5,
      "exploring": 72
    },
    "regimeAxisAdj": {
      "coherent": 10,
      "exploring": 51
    },
    "regimeTightenBudget": {
      "coherent": 0,
      "exploring": 84
    },
    "coherentFreezeBeats": 3,
    "skippedColdspotRelaxations": 11,
    "coldspotSkipReasons": {
      "coherentFreeze": 8,
      "phaseHot": 0,
      "trustHot": 3,
      "residual": 0
    },
    "phaseSurfaceHotBeats": 55,
    "trustSurfaceHotBeats": 59,
    "entropySurfaceHotBeats": 59,
    "coherentHotspotActuationBeats": 3,
    "coherentHotspotPairAdj": 5,
    "coherentHotspotAxisAdj": 0,
    "warmupTicks": 6,
    "warmupRemaining": 0
  },
  "outputLoadGuard": null,
  "profilerCadence": {
    "cadence": "measure-recorder",
    "analysisTicks": 190,
    "regimeTicks": 190,
    "snapshotReuseEntries": 214,
    "warmupEntries": 4,
    "escalatedEntries": 167,
    "analysisSources": {
      "measure-recorder": 237,
      "beat-escalation": 167
    },
    "telemetryBeatSpanAvg": 1,
    "telemetryBeatSpanMax": 1
  },
  "regimeCadence": {
    "traceEntries": 408,
    "profilerTicks": 190,
    "traceEntriesPerProfilerTick": 2.15,
    "traceEntryCounts": {
      "initializing": 4,
      "evolving": 4,
      "coherent": 82,
      "exploring": 314
    },
    "profilerTickResolvedCounts": {
      "evolving": 4,
      "coherent": 32,
      "exploring": 179
    },
    "profilerTickRawCounts": {
      "coherent": 36,
      "exploring": 179
    },
    "snapshotReuseEntries": 214,
    "warmupEntries": 4
  },
  "forcedTransitionEvents": [
    {
      "eventId": 1,
      "from": "coherent",
      "to": "exploring",
      "reason": "coherent-cadence-monopoly",
      "triggerTick": 41,
      "triggerStreak": 33,
      "runTickCount": 36,
      "runTransitionCount": 1,
      "runCoherentBeats": 32,
      "runCoherentShare": 0.8889,
      "forcedBeatsRemaining": 8
    }
  ],
  "transitionReadiness": {
    "gapMin": -0.0072,
    "gapMax": 0.8025,
    "gapAvg": 0.2948,
    "velocityBlockedBeats": 0,
    "totalBeats": 404,
    "velocityBlockedRate": 0,
    "finalThresholdScale": 0.55,
    "evolvingBeats": 0,
    "coherentBeats": 32,
    "runCoherentBeats": 32,
    "maxCoherentBeats": 32,
    "runBeatCount": 215,
    "runTickCount": 215,
    "runCoherentShare": 0.1488,
    "runTransitionCount": 2,
    "forcedBreakCount": 1,
    "forcedRegime": "",
    "forcedRegimeBeatsRemaining": 0,
    "forcedOverrideBeats": 8,
    "lastForcedReason": "coherent-cadence-monopoly",
    "lastForcedTriggerStreak": 33,
    "lastForcedTriggerBeat": 41,
    "cadenceMonopolyPressure": 0.1597,
    "cadenceMonopolyActive": false,
    "cadenceMonopolyReason": "transition-scarcity",
    "rawExploringShare": 0.8318,
    "rawEvolvingShare": 0,
    "rawNonCoherentOpportunityShare": 0.8318,
    "resolvedNonCoherentShare": 0.8505,
    "opportunityGap": 0,
    "tickSource": "profiler-recorder",
    "exploringBlock": {
      "velocity": 4,
      "dimension": 18,
      "coupling": 0,
      "none": 382
    },
    "coherentBlock": {
      "velocity": 0,
      "dimension": 0,
      "coupling": 5,
      "none": 399
    },
    "coherentBlockPairs": {
      "tension-trust": 1,
      "entropy-trust": 1
    },
    "rawRegimeCounts": {
      "coherent": 36,
      "exploring": 179
    },
    "runRawRegimeCounts": {
      "coherent": 36,
      "exploring": 179
    },
    "runResolvedRegimeCounts": {
      "evolving": 4,
      "coherent": 32,
      "exploring": 179
    },
    "rawRegimeMaxStreak": {
      "coherent": 36,
      "exploring": 179
    },
    "effectiveDimHistogram": {
      "p10": 2.9809,
      "p25": 3.0465,
      "p50": 3.3576,
      "p75": 3.5555,
      "p90": 3.7151,
      "min": 0,
      "max": 3.8056,
      "count": 404
    }
  },
  "pairExceedanceBeats": {
    "density-tension": 13,
    "density-flicker": 20,
    "density-entropy": 1,
    "density-trust": 1,
    "tension-flicker": 15,
    "tension-entropy": 2,
    "tension-trust": 2,
    "flicker-entropy": 3,
    "flicker-trust": 2,
    "entropy-trust": 2
  },
  "exceedanceComposite": {
    "uniqueBeats": 20,
    "uniqueRate": 0.049,
    "totalPairExceedanceBeats": 61,
    "topPairs": [
      {
        "pair": "density-flicker",
        "beats": 20
      },
      {
        "pair": "tension-flicker",
        "beats": 15
      },
      {
        "pair": "density-tension",
        "beats": 13
      }
    ],
    "bySection": {
      "0": 20
    },
    "bySectionPair": {
      "0": {
        "density-tension": 13,
        "density-flicker": 20,
        "density-entropy": 1,
        "density-trust": 1,
        "tension-flicker": 15,
        "tension-entropy": 2,
        "tension-trust": 2,
        "flicker-entropy": 3,
        "flicker-trust": 2,
        "entropy-trust": 2
      }
    }
  },
  "guardCouplingInteraction": {
    "guardedBeats": 0,
    "unguardedBeats": 404,
    "guardedExceedanceRate": 0,
    "unguardedExceedanceRate": 0.0495,
    "exceedanceDelta": -0.0495,
    "perPair": {
      "density-tension": {
        "guardedAvg": 0,
        "unguardedAvg": 0.3623,
        "delta": -0.3623
      },
      "density-flicker": {
        "guardedAvg": 0,
        "unguardedAvg": 0.3764,
        "delta": -0.3764
      },
      "density-entropy": {
        "guardedAvg": 0,
        "unguardedAvg": 0.2611,
        "delta": -0.2611
      },
      "density-trust": {
        "guardedAvg": 0,
        "unguardedAvg": 0.3248,
        "delta": -0.3248
      },
      "density-phase": {
        "guardedAvg": 0,
        "unguardedAvg": 0.049,
        "delta": -0.049
      },
      "tension-flicker": {
        "guardedAvg": 0,
        "unguardedAvg": 0.2344,
        "delta": -0.2344
      },
      "tension-entropy": {
        "guardedAvg": 0,
        "unguardedAvg": 0.3118,
        "delta": -0.3118
      },
      "tension-trust": {
        "guardedAvg": 0,
        "unguardedAvg": 0.3179,
        "delta": -0.3179
      },
      "tension-phase": {
        "guardedAvg": 0,
        "unguardedAvg": 0.0538,
        "delta": -0.0538
      },
      "flicker-entropy": {
        "guardedAvg": 0,
        "unguardedAvg": 0.2719,
        "delta": -0.2719
      },
      "flicker-trust": {
        "guardedAvg": 0,
        "unguardedAvg": 0.4201,
        "delta": -0.4201
      },
      "flicker-phase": {
        "guardedAvg": 0,
        "unguardedAvg": 0.0448,
        "delta": -0.0448
      },
      "entropy-trust": {
        "guardedAvg": 0,
        "unguardedAvg": 0.2752,
        "delta": -0.2752
      },
      "entropy-phase": {
        "guardedAvg": 0,
        "unguardedAvg": 0.0349,
        "delta": -0.0349
      }
    }
  },
  "tailRecovery": {
    "stickyTailPressure": 0.6508,
    "densityFlickerTailPressure": 0.6372,
    "tailRecoveryDrive": 0.6169,
    "tailRecoveryTrigger": 0.2168,
    "tailRecoveryHandshake": 0.97,
    "handshakeSaturationBeats": 0,
    "handshakeBeatToSaturation": -1,
    "handshakeEffectiveRange": 0.8028,
    "tailRecoveryCap": 0.6198,
    "tailRecoveryCeilingPressure": 0,
    "dominantTailPair": "density-flicker",
    "tailHotspotCount": 12,
    "floorRecoveryActive": true,
    "floorRecoveryTicksRemaining": 26,
    "floorContactBeats": 5,
    "persistentPairCount": 13,
    "activePairCount": 12,
    "topPairs": [
      {
        "pair": "density-flicker",
        "pressure": 0.6372
      },
      {
        "pair": "density-tension",
        "pressure": 0.5375
      },
      {
        "pair": "tension-flicker",
        "pressure": 0.4528
      },
      {
        "pair": "tension-entropy",
        "pressure": 0.4318
      },
      {
        "pair": "flicker-trust",
        "pressure": 0.3896
      }
    ]
  },
  "cadenceMonopoly": {
    "pressure": 0.1597,
    "active": false,
    "reason": "transition-scarcity",
    "rawExploringShare": 0.8318,
    "rawEvolvingShare": 0,
    "rawNonCoherentOpportunityShare": 0.8318,
    "resolvedNonCoherentShare": 0.8505,
    "opportunityGap": 0
  },
  "phaseTelemetry": {
    "entries": 404,
    "validEntries": 404,
    "invalidEntries": 0,
    "validRate": 1,
    "changedEntries": 98,
    "changedRate": 0.2426,
    "maxStaleBeats": 6,
    "staleEntries": 305,
    "staleRate": 0.755,
    "avgCouplingCoverage": 0.198,
    "zeroCouplingCoverageEntries": 324,
    "maxAvailablePairs": 4,
    "maxMissingPairs": 4,
    "varianceGatedEntries": 320,
    "varianceGatedRate": 0.7921,
    "pairStateCounts": {
      "warmup": 16,
      "variance-gated": 1280,
      "available": 320
    },
    "pairStateDetailCounts": {
      "density-phase": {
        "warmup": 4,
        "variance-gated": 320,
        "available": 80
      },
      "tension-phase": {
        "warmup": 4,
        "variance-gated": 320,
        "available": 80
      },
      "flicker-phase": {
        "warmup": 4,
        "variance-gated": 320,
        "available": 80
      },
      "entropy-phase": {
        "warmup": 4,
        "variance-gated": 320,
        "available": 80
      }
    },
    "integrity": "warning"
  },
  "telemetryHealth": {
    "score": 0.5171,
    "phaseTelemetryPresent": true,
    "phaseIntegrity": "warning",
    "underSeenPairCount": 4,
    "maxGap": 0.3741,
    "progressIntegrity": "warning",
    "phaseStaleRate": 0.755,
    "profilerBeatSpanAvg": 1,
    "profilerBeatSpanMax": 1
  },
  "progressIntegrity": {
    "duplicateLayerBeatKeys": 0,
    "overfullBeatKeys": 0,
    "l1ProgressRegressions": 0,
    "l1TimeRegressions": 0,
    "pairedBeatKeys": 89,
    "pairedBeatKeyRatio": 0.2825,
    "integrity": "warning"
  },
  "adaptiveTelemetryReconciliation": {
    "underSeenPairCount": 4,
    "maxGap": 0.3741,
    "pairs": [
      {
        "pair": "density-flicker",
        "traceP95": 0.9501,
        "controllerP95": 0.576,
        "recentP95": 0.576,
        "gap": 0.3741,
        "recentGap": 0.3741,
        "telemetryWindowBeats": 59
      },
      {
        "pair": "density-trust",
        "traceP95": 0.77,
        "controllerP95": 0.419,
        "recentP95": 0.453,
        "gap": 0.351,
        "recentGap": 0.317,
        "telemetryWindowBeats": 48
      },
      {
        "pair": "density-tension",
        "traceP95": 0.7383,
        "controllerP95": 0.543,
        "recentP95": 0.466,
        "gap": 0.1953,
        "recentGap": 0.2723,
        "telemetryWindowBeats": 54
      },
      {
        "pair": "flicker-trust",
        "traceP95": 0.824,
        "controllerP95": 0.666,
        "recentP95": 0.407,
        "gap": 0.158,
        "recentGap": 0.417,
        "telemetryWindowBeats": 56
      }
    ]
  },
  "nonNudgeableGains": {
    "pairCount": 2,
    "nonZeroGainPairs": 0,
    "nonZeroEffectiveGainPairs": 0,
    "pairs": [
      {
        "pair": "entropy-trust",
        "gain": 0,
        "effectiveGain": 0,
        "rawRollingAbsCorr": 0.1742,
        "rawEmaMax": 0.2908
      },
      {
        "pair": "trust-phase",
        "gain": 0,
        "effectiveGain": 0,
        "rawRollingAbsCorr": 0,
        "rawEmaMax": 0
      }
    ]
  },
  "trustDominance": {
    "dominantSystems": [
      {
        "system": "coherenceMonitor",
        "score": 0.5445,
        "weight": 1.4132
      },
      {
        "system": "phaseLock",
        "score": 0.4654,
        "weight": 1.3473
      },
      {
        "system": "stutterContagion",
        "score": 0.3852,
        "weight": 1.2329
      }
    ],
    "dominantCountAbove06": 0,
    "dominanceSpread": 0.0791,
    "dominantWeightSpread": 0.0659,
    "dominantSystem": "coherenceMonitor",
    "dominantScore": 0.5445,
    "dominantWeight": 1.4132,
    "coherenceMonitor": {
      "system": "coherenceMonitor",
      "score": 0.5445,
      "weight": 1.4132
    },
    "pairAwareSystems": [
      {
        "system": "stutterContagion",
        "hotspotPressure": 0.4638,
        "dominantPair": "density-flicker",
        "dominantPairCount": 389
      },
      {
        "system": "feedbackOscillator",
        "hotspotPressure": 0.2616,
        "dominantPair": "tension-flicker",
        "dominantPairCount": 279
      },
      {
        "system": "coherenceMonitor",
        "hotspotPressure": 0.0764,
        "dominantPair": "density-trust",
        "dominantPairCount": 156
      },
      {
        "system": "restSynchronizer",
        "hotspotPressure": 0.0727,
        "dominantPair": "density-trust",
        "dominantPairCount": 159
      },
      {
        "system": "convergence",
        "hotspotPressure": 0.0624,
        "dominantPair": "density-trust",
        "dominantPairCount": 175
      }
    ],
    "trustAxisShare": 0.1792,
    "trustPairExceedanceBeats": 7,
    "trustHotspotPairs": [
      {
        "pair": "tension-trust",
        "beats": 2
      },
      {
        "pair": "flicker-trust",
        "beats": 2
      },
      {
        "pair": "entropy-trust",
        "beats": 2
      },
      {
        "pair": "density-trust",
        "beats": 1
      }
    ]
  },
  "intraAxisDistribution": {
    "density": {
      "gini": 0.2202,
      "pairCount": 5,
      "dominant": "density-flicker",
      "dominantAvg": 0.3764,
      "pairs": [
        {
          "pair": "density-phase",
          "avg": 0.049
        },
        {
          "pair": "density-entropy",
          "avg": 0.2611
        },
        {
          "pair": "density-trust",
          "avg": 0.3248
        },
        {
          "pair": "density-tension",
          "avg": 0.3623
        },
        {
          "pair": "density-flicker",
          "avg": 0.3764
        }
      ]
    },
    "tension": {
      "gini": 0.2189,
      "pairCount": 5,
      "dominant": "density-tension",
      "dominantAvg": 0.3623,
      "pairs": [
        {
          "pair": "tension-phase",
          "avg": 0.0538
        },
        {
          "pair": "tension-flicker",
          "avg": 0.2344
        },
        {
          "pair": "tension-entropy",
          "avg": 0.3118
        },
        {
          "pair": "tension-trust",
          "avg": 0.3179
        },
        {
          "pair": "density-tension",
          "avg": 0.3623
        }
      ]
    },
    "flicker": {
      "gini": 0.2649,
      "pairCount": 5,
      "dominant": "flicker-trust",
      "dominantAvg": 0.4201,
      "pairs": [
        {
          "pair": "flicker-phase",
          "avg": 0.0448
        },
        {
          "pair": "tension-flicker",
          "avg": 0.2344
        },
        {
          "pair": "flicker-entropy",
          "avg": 0.2719
        },
        {
          "pair": "density-flicker",
          "avg": 0.3764
        },
        {
          "pair": "flicker-trust",
          "avg": 0.4201
        }
      ]
    },
    "entropy": {
      "gini": 0.1967,
      "pairCount": 5,
      "dominant": "tension-entropy",
      "dominantAvg": 0.3118,
      "pairs": [
        {
          "pair": "entropy-phase",
          "avg": 0.0349
        },
        {
          "pair": "density-entropy",
          "avg": 0.2611
        },
        {
          "pair": "flicker-entropy",
          "avg": 0.2719
        },
        {
          "pair": "entropy-trust",
          "avg": 0.2752
        },
        {
          "pair": "tension-entropy",
          "avg": 0.3118
        }
      ]
    },
    "trust": {
      "gini": 0.0825,
      "pairCount": 4,
      "dominant": "flicker-trust",
      "dominantAvg": 0.4201,
      "pairs": [
        {
          "pair": "entropy-trust",
          "avg": 0.2752
        },
        {
          "pair": "tension-trust",
          "avg": 0.3179
        },
        {
          "pair": "density-trust",
          "avg": 0.3248
        },
        {
          "pair": "flicker-trust",
          "avg": 0.4201
        }
      ]
    },
    "phase": {
      "gini": 0.0834,
      "pairCount": 4,
      "dominant": "tension-phase",
      "dominantAvg": 0.0538,
      "pairs": [
        {
          "pair": "entropy-phase",
          "avg": 0.0349
        },
        {
          "pair": "flicker-phase",
          "avg": 0.0448
        },
        {
          "pair": "density-phase",
          "avg": 0.049
        },
        {
          "pair": "tension-phase",
          "avg": 0.0538
        }
      ]
    }
  },
  "diagnosticArc": [
    {
      "snapshotIndex": 1,
      "beatKey": "0:periodic:40",
      "timeMs": 7647.058823529412,
      "effectiveDim": 2.99,
      "globalGainMultiplier": 0.3299,
      "regime": "coherent",
      "couplingStrength": 0.304,
      "phaseIntegrity": "warning",
      "trust": {
        "stutterContagion": {
          "score": 0.1104794545491314,
          "samples": 40,
          "weight": 0.9793871183088116,
          "hotspotPressure": 0.6577,
          "dominantPair": "density-flicker",
          "hotspotPairs": [
            {
              "pair": "density-flicker",
              "pressure": 0.7986,
              "severePressure": 0.4609
            },
            {
              "pair": "flicker-trust",
              "pressure": 0.0941,
              "severePressure": 0
            }
          ],
          "severePressure": 0.4609,
          "severePair": "density-flicker"
        },
        "cadenceAlignment": {
          "score": 0.11055601693119306,
          "samples": 40,
          "weight": 1.1220810168738304,
          "hotspotPressure": 0.275,
          "dominantPair": "density-trust",
          "hotspotPairs": [
            {
              "pair": "density-trust",
              "pressure": 0.275,
              "severePressure": 0
            }
          ],
          "severePressure": 0,
          "severePair": ""
        },
        "phaseLock": {
          "score": 0.24117966744991298,
          "samples": 40,
          "weight": 1.1803009285205759,
          "hotspotPressure": 0,
          "dominantPair": "",
          "hotspotPairs": [],
          "severePressure": 0,
          "severePair": ""
        },
        "convergence": {
          "score": 0.19646809572400206,
          "samples": 40,
          "weight": 1.1428580213056134,
          "hotspotPressure": 0.28,
          "dominantPair": "density-trust",
          "hotspotPairs": [
            {
              "pair": "density-trust",
              "pressure": 0.28,
              "severePressure": 0
            }
          ],
          "severePressure": 0,
          "severePair": ""
        },
        "feedbackOscillator": {
          "score": 0.23445104176432643,
          "samples": 40,
          "weight": 1.1670571275405695,
          "hotspotPressure": 0.1765,
          "dominantPair": "tension-flicker",
          "hotspotPairs": [
            {
              "pair": "tension-flicker",
              "pressure": 0.1967,
              "severePressure": 0.295
            },
            {
              "pair": "flicker-trust",
              "pressure": 0.0958,
              "severePressure": 0
            }
          ],
          "severePressure": 0.295,
          "severePair": "tension-flicker"
        },
        "coherenceMonitor": {
          "score": 0.47952,
          "samples": 40,
          "weight": 1.2518787452483708,
          "hotspotPressure": 0.2597,
          "dominantPair": "density-trust",
          "hotspotPairs": [
            {
              "pair": "density-trust",
              "pressure": 0.3,
              "severePressure": 0
            },
            {
              "pair": "flicker-trust",
              "pressure": 0.0984,
              "severePressure": 0
            }
          ],
          "severePressure": 0,
          "severePair": ""
        },
        "entropyRegulator": {
          "score": 0.148190165965013,
          "samples": 40,
          "weight": 1.111785216383109,
          "hotspotPressure": 0.0582,
          "dominantPair": "density-entropy",
          "hotspotPairs": [
            {
              "pair": "density-entropy",
              "pressure": 0.059,
              "severePressure": 0
            },
            {
              "pair": "tension-entropy",
              "pressure": 0.055,
              "severePressure": 0
            }
          ],
          "severePressure": 0,
          "severePair": ""
        },
        "restSynchronizer": {
          "score": 0.2203663584536219,
          "samples": 40,
          "weight": 1.1601497390620297,
          "hotspotPressure": 0.2488,
          "dominantPair": "density-trust",
          "hotspotPairs": [
            {
              "pair": "density-trust",
              "pressure": 0.2875,
              "severePressure": 0
            },
            {
              "pair": "flicker-trust",
              "pressure": 0.0941,
              "severePressure": 0
            }
          ],
          "severePressure": 0,
          "severePair": ""
        }
      },
      "trustVelocity": {},
      "activeProfile": "default",
      "couplingMeans": {
        "density-tension": 0.288,
        "density-flicker": 0.895,
        "density-entropy": 0.158,
        "density-trust": 0.765,
        "tension-flicker": 0.088,
        "tension-entropy": 0.19,
        "tension-trust": 0.195,
        "flicker-entropy": 0.208,
        "flicker-trust": 0.736,
        "entropy-trust": 0.227
      }
    },
    {
      "snapshotIndex": 2,
      "beatKey": "0:end",
      "timeMs": 7647.058823529412,
      "effectiveDim": 3.05,
      "globalGainMultiplier": 0.3441,
      "regime": "coherent",
      "couplingStrength": 0.296,
      "phaseIntegrity": "warning",
      "trust": {
        "stutterContagion": {
          "score": 0.15810681707372734,
          "samples": 80,
          "weight": 1.0198983993387403,
          "hotspotPressure": 0.8691,
          "dominantPair": "density-flicker",
          "hotspotPairs": [
            {
              "pair": "density-flicker",
              "pressure": 1.0674,
              "severePressure": 0.8635
            },
            {
              "pair": "flicker-trust",
              "pressure": 0.0756,
              "severePressure": 0
            }
          ],
          "severePressure": 0.8635,
          "severePair": "density-flicker"
        },
        "cadenceAlignment": {
          "score": 0.15810681707372734,
          "samples": 80,
          "weight": 1.1277991773511524,
          "hotspotPressure": 0.132,
          "dominantPair": "density-trust",
          "hotspotPairs": [
            {
              "pair": "density-trust",
              "pressure": 0.132,
              "severePressure": 0
            }
          ],
          "severePressure": 0,
          "severePair": ""
        },
        "phaseLock": {
          "score": 0.5377868380146118,
          "samples": 80,
          "weight": 1.4040036557288833,
          "hotspotPressure": 0,
          "dominantPair": "",
          "hotspotPairs": [],
          "severePressure": 0,
          "severePair": ""
        },
        "convergence": {
          "score": 0.19163059107815678,
          "samples": 80,
          "weight": 1.1422879963031858,
          "hotspotPressure": 0.1344,
          "dominantPair": "density-trust",
          "hotspotPairs": [
            {
              "pair": "density-trust",
              "pressure": 0.1344,
              "severePressure": 0
            }
          ],
          "severePressure": 0,
          "severePair": ""
        },
        "feedbackOscillator": {
          "score": 0.26969033558686945,
          "samples": 80,
          "weight": 1.1757696474164647,
          "hotspotPressure": 0.3968,
          "dominantPair": "tension-flicker",
          "hotspotPairs": [
            {
              "pair": "tension-flicker",
              "pressure": 0.4768,
              "severePressure": 0.7223
            },
            {
              "pair": "flicker-trust",
              "pressure": 0.077,
              "severePressure": 0
            }
          ],
          "severePressure": 0.7223,
          "severePair": "tension-flicker"
        },
        "coherenceMonitor": {
          "score": 0.5259337476068212,
          "samples": 80,
          "weight": 1.4021752364103945,
          "hotspotPressure": 0.131,
          "dominantPair": "density-trust",
          "hotspotPairs": [
            {
              "pair": "density-trust",
              "pressure": 0.144,
              "severePressure": 0
            },
            {
              "pair": "flicker-trust",
              "pressure": 0.0791,
              "severePressure": 0
            }
          ],
          "severePressure": 0,
          "severePair": ""
        },
        "entropyRegulator": {
          "score": 0.15810681707372734,
          "samples": 80,
          "weight": 1.1024390271392834,
          "hotspotPressure": 0.0349,
          "dominantPair": "density-entropy",
          "hotspotPairs": [
            {
              "pair": "density-entropy",
              "pressure": 0.0354,
              "severePressure": 0
            },
            {
              "pair": "tension-entropy",
              "pressure": 0.033,
              "severePressure": 0
            }
          ],
          "severePressure": 0,
          "severePair": ""
        },
        "restSynchronizer": {
          "score": 0.2047295867717487,
          "samples": 80,
          "weight": 1.149099223694238,
          "hotspotPressure": 0.1255,
          "dominantPair": "density-trust",
          "hotspotPairs": [
            {
              "pair": "density-trust",
              "pressure": 0.138,
              "severePressure": 0
            },
            {
              "pair": "flicker-trust",
              "pressure": 0.0756,
              "severePressure": 0
            }
          ],
          "severePressure": 0,
          "severePair": ""
        }
      },
      "trustVelocity": {
        "stutterContagion": 0.0476,
        "cadenceAlignment": 0.0476,
        "phaseLock": 0.2966,
        "convergence": -0.0048,
        "feedbackOscillator": 0.0352,
        "coherenceMonitor": 0.0464,
        "entropyRegulator": 0.0099,
        "restSynchronizer": -0.0156
      },
      "activeProfile": "default",
      "couplingMeans": {
        "density-tension": 0.308,
        "density-flicker": 0.852,
        "density-entropy": 0.184,
        "density-trust": 0.5,
        "tension-flicker": 0.028,
        "tension-entropy": 0.172,
        "tension-trust": 0.047,
        "flicker-entropy": 0.234,
        "flicker-trust": 0.674,
        "entropy-trust": 0.408
      }
    },
    {
      "snapshotIndex": 3,
      "beatKey": "1:end",
      "timeMs": 23509.803921568626,
      "effectiveDim": 3.48,
      "globalGainMultiplier": 0.6173,
      "regime": "exploring",
      "couplingStrength": 0.3,
      "phaseIntegrity": "warning",
      "trust": {
        "stutterContagion": {
          "score": 0.6245169338336417,
          "samples": 208,
          "weight": 1.3812880618428456,
          "hotspotPressure": 0.4267,
          "dominantPair": "density-flicker",
          "hotspotPairs": [
            {
              "pair": "density-flicker",
              "pressure": 0.4267,
              "severePressure": 0.7365
            }
          ],
          "severePressure": 0.7365,
          "severePair": "density-flicker"
        },
        "cadenceAlignment": {
          "score": 0.2284465728162872,
          "samples": 208,
          "weight": 1.149927002965901,
          "hotspotPressure": 0,
          "dominantPair": "",
          "hotspotPairs": [],
          "severePressure": 0,
          "severePair": ""
        },
        "phaseLock": {
          "score": 0.5652168204365657,
          "samples": 208,
          "weight": 1.4247084739813678,
          "hotspotPressure": 0,
          "dominantPair": "",
          "hotspotPairs": [],
          "severePressure": 0,
          "severePair": ""
        },
        "convergence": {
          "score": 0.26344606100171464,
          "samples": 208,
          "weight": 1.19238192869772,
          "hotspotPressure": 0,
          "dominantPair": "",
          "hotspotPairs": [],
          "severePressure": 0,
          "severePair": ""
        },
        "feedbackOscillator": {
          "score": 0.2674884917061453,
          "samples": 208,
          "weight": 1.1840552146240195,
          "hotspotPressure": 0.3611,
          "dominantPair": "tension-flicker",
          "hotspotPairs": [
            {
              "pair": "tension-flicker",
              "pressure": 0.3611,
              "severePressure": 0.4607
            }
          ],
          "severePressure": 0.4607,
          "severePair": "tension-flicker"
        },
        "coherenceMonitor": {
          "score": 0.6062483163765982,
          "samples": 208,
          "weight": 1.477278923324368,
          "hotspotPressure": 0,
          "dominantPair": "",
          "hotspotPairs": [],
          "severePressure": 0,
          "severePair": ""
        },
        "entropyRegulator": {
          "score": 0.22761250449022058,
          "samples": 208,
          "weight": 1.1366057194721146,
          "hotspotPressure": 0,
          "dominantPair": "",
          "hotspotPairs": [],
          "severePressure": 0,
          "severePair": ""
        },
        "restSynchronizer": {
          "score": 0.24902041812390513,
          "samples": 208,
          "weight": 1.1842141282585128,
          "hotspotPressure": 0,
          "dominantPair": "",
          "hotspotPairs": [],
          "severePressure": 0,
          "severePair": ""
        }
      },
      "trustVelocity": {
        "stutterContagion": 0.4664,
        "cadenceAlignment": 0.0703,
        "phaseLock": 0.0274,
        "convergence": 0.0718,
        "feedbackOscillator": -0.0022,
        "coherenceMonitor": 0.0803,
        "entropyRegulator": 0.0695,
        "restSynchronizer": 0.0443
      },
      "activeProfile": "restrained",
      "couplingMeans": {
        "density-tension": 0.374,
        "density-flicker": 0.249,
        "density-entropy": 0.213,
        "tension-flicker": 0.32,
        "tension-entropy": 0.481,
        "flicker-entropy": 0.166
      }
    },
    {
      "snapshotIndex": 4,
      "beatKey": "2:end",
      "timeMs": 51984.55139631611,
      "effectiveDim": 3.44,
      "globalGainMultiplier": 0.6197,
      "regime": "exploring",
      "couplingStrength": 0.322,
      "phaseIntegrity": "warning",
      "trust": {
        "stutterContagion": {
          "score": 0.3126743984358772,
          "samples": 404,
          "weight": 1.233931866725643,
          "hotspotPressure": 0,
          "dominantPair": "",
          "hotspotPairs": [],
          "severePressure": 0,
          "severePair": ""
        },
        "cadenceAlignment": {
          "score": 0.15412279973612916,
          "samples": 404,
          "weight": 1.1324499999999809,
          "hotspotPressure": 0,
          "dominantPair": "",
          "hotspotPairs": [],
          "severePressure": 0,
          "severePair": ""
        },
        "phaseLock": {
          "score": 0.39798916542252455,
          "samples": 404,
          "weight": 1.2990005125611945,
          "hotspotPressure": 0,
          "dominantPair": "",
          "hotspotPairs": [],
          "severePressure": 0,
          "severePair": ""
        },
        "convergence": {
          "score": 0.21241287361341923,
          "samples": 404,
          "weight": 1.1595987446427718,
          "hotspotPressure": 0,
          "dominantPair": "",
          "hotspotPairs": [],
          "severePressure": 0,
          "severePair": ""
        },
        "feedbackOscillator": {
          "score": 0.2697310142662274,
          "samples": 404,
          "weight": 1.202661944479397,
          "hotspotPressure": 0,
          "dominantPair": "",
          "hotspotPairs": [],
          "severePressure": 0,
          "severePair": ""
        },
        "coherenceMonitor": {
          "score": 0.5136462660550232,
          "samples": 404,
          "weight": 1.4205174520547708,
          "hotspotPressure": 0,
          "dominantPair": "",
          "hotspotPairs": [],
          "severePressure": 0,
          "severePair": ""
        },
        "entropyRegulator": {
          "score": 0.2666797057565394,
          "samples": 404,
          "weight": 1.2001339454978346,
          "hotspotPressure": 0,
          "dominantPair": "",
          "hotspotPairs": [],
          "severePressure": 0,
          "severePair": ""
        },
        "restSynchronizer": {
          "score": 0.30072821575361625,
          "samples": 404,
          "weight": 1.2259589917771252,
          "hotspotPressure": 0,
          "dominantPair": "",
          "hotspotPairs": [],
          "severePressure": 0,
          "severePair": ""
        }
      },
      "trustVelocity": {
        "stutterContagion": -0.3118,
        "cadenceAlignment": -0.0743,
        "phaseLock": -0.1672,
        "convergence": -0.051,
        "feedbackOscillator": 0.0022,
        "coherenceMonitor": -0.0926,
        "entropyRegulator": 0.0391,
        "restSynchronizer": 0.0517
      },
      "activeProfile": "default",
      "couplingMeans": {
        "density-tension": 0.38,
        "density-flicker": 0.306,
        "density-entropy": 0.367,
        "density-trust": 0.024,
        "tension-flicker": 0.436,
        "tension-entropy": 0.304,
        "tension-trust": 0.225,
        "flicker-entropy": 0.143,
        "flicker-trust": 0.126,
        "entropy-trust": 0.026
      }
    }
  ],
  "trustTurbulenceEvents": [
    {
      "snapshotIndex": 2,
      "beatKey": "0:end",
      "system": "phaseLock",
      "velocity": 0.2966
    },
    {
      "snapshotIndex": 3,
      "beatKey": "1:end",
      "system": "stutterContagion",
      "velocity": 0.4664
    },
    {
      "snapshotIndex": 4,
      "beatKey": "2:end",
      "system": "stutterContagion",
      "velocity": -0.3118
    },
    {
      "snapshotIndex": 4,
      "beatKey": "2:end",
      "system": "phaseLock",
      "velocity": -0.1672
    }
  ],
  "trustVelocityRange": {
    "stutterContagion": {
      "min": -0.3118,
      "max": 0.4664,
      "snapshots": 3
    },
    "cadenceAlignment": {
      "min": -0.0743,
      "max": 0.0703,
      "snapshots": 3
    },
    "phaseLock": {
      "min": -0.1672,
      "max": 0.2966,
      "snapshots": 3
    },
    "convergence": {
      "min": -0.051,
      "max": 0.0718,
      "snapshots": 3
    },
    "feedbackOscillator": {
      "min": -0.0022,
      "max": 0.0352,
      "snapshots": 3
    },
    "coherenceMonitor": {
      "min": -0.0926,
      "max": 0.0803,
      "snapshots": 3
    },
    "entropyRegulator": {
      "min": 0.0099,
      "max": 0.0695,
      "snapshots": 3
    },
    "restSynchronizer": {
      "min": -0.0156,
      "max": 0.0517,
      "snapshots": 3
    }
  },
  "trustVelocityAtExceedance": {
    "stutterContagion": {
      "min": 0.0476,
      "max": 0.0476,
      "snapshots": 1
    },
    "cadenceAlignment": {
      "min": 0.0476,
      "max": 0.0476,
      "snapshots": 1
    },
    "phaseLock": {
      "min": 0.2966,
      "max": 0.2966,
      "snapshots": 1
    },
    "convergence": {
      "min": -0.0048,
      "max": -0.0048,
      "snapshots": 1
    },
    "feedbackOscillator": {
      "min": 0.0352,
      "max": 0.0352,
      "snapshots": 1
    },
    "coherenceMonitor": {
      "min": 0.0464,
      "max": 0.0464,
      "snapshots": 1
    },
    "entropyRegulator": {
      "min": 0.0099,
      "max": 0.0099,
      "snapshots": 1
    },
    "restSynchronizer": {
      "min": -0.0156,
      "max": -0.0156,
      "snapshots": 1
    }
  }
}
