{
  "meta": {
    "generated": "2026-03-08T02:18:01.320Z",
    "currentRun": "2026-03-08T02:18:01.319Z",
    "previousRun": "2026-03-08T01:12:45.882Z"
  },
  "verdict": "EVOLVED",
  "driftedDimensions": 1,
  "totalDimensions": 11,
  "tolerances": {
    "noteCountRatio": 0.35,
    "pitchEntropyDelta": 0.25,
    "densityVarianceDelta": 0.2,
    "tensionArcDistortion": 0.3,
    "trustConvergenceDelta": 0.25,
    "regimeDistributionDelta": 0.2,
    "couplingDelta": 0.25,
    "exceedanceSeverity": 35,
    "hotspotMigration": 0.55,
    "telemetryHealthDelta": 0.35
  },
  "dimensions": [
    {
      "dimension": "noteCount",
      "delta": 0.833817245577116,
      "tolerance": 0.5,
      "status": "drifted",
      "current": 17951,
      "previous": 21447,
      "currentNotesPerBeat": 43.4649,
      "previousNotesPerBeat": 261.5488,
      "currentGuardedRate": 0.953,
      "previousGuardedRate": 0.94,
      "currentAvgGuardScale": 0.4189,
      "previousAvgGuardScale": 0.74,
      "perLayer": {
        "currentL1": 7926,
        "currentL2": 10025,
        "previousL1": 8255,
        "previousL2": 13192
      }
    },
    {
      "dimension": "pitchEntropy",
      "delta": 0.23703887476729957,
      "tolerance": 0.25,
      "status": "stable",
      "current": 6.480584074148684,
      "previous": 6.243545199381384
    },
    {
      "dimension": "densityVariance",
      "delta": 0.0064188995337127516,
      "tolerance": 0.2,
      "status": "stable",
      "current": 0.007048504565280496,
      "previous": 0.0006296050315677438
    },
    {
      "dimension": "tensionArc",
      "delta": 0.11007930132752276,
      "tolerance": 0.35,
      "status": "stable",
      "current": [
        0.36326956976470026,
        0.6056315305318521,
        0.6579074869356779,
        0.6208069905759384
      ],
      "previous": [
        0.3261146771272436,
        0.48161506943373644,
        0.5122257598070736,
        0.5184054474545199
      ]
    },
    {
      "dimension": "trustConvergence",
      "delta": 0.03583750000000008,
      "tolerance": 0.25,
      "status": "stable",
      "current": 0.32165000000000005,
      "previous": 0.28581249999999997
    },
    {
      "dimension": "regimeDistribution",
      "delta": 0.13820557491289198,
      "tolerance": 0.3,
      "status": "stable"
    },
    {
      "dimension": "coupling",
      "delta": 0.1559642857142857,
      "tolerance": 0.25,
      "status": "stable"
    },
    {
      "dimension": "correlationTrend",
      "delta": 0.5,
      "tolerance": 1,
      "status": "stable",
      "flipDetails": [
        {
          "pair": "density-entropy",
          "from": "increasing",
          "to": "stable"
        },
        {
          "pair": "entropy-phase",
          "from": "stable",
          "to": "increasing"
        },
        {
          "pair": "entropy-trust",
          "from": "decreasing",
          "to": "stable"
        },
        {
          "pair": "flicker-entropy",
          "from": "increasing",
          "to": "decreasing"
        },
        {
          "pair": "flicker-phase",
          "from": "stable",
          "to": "increasing"
        },
        {
          "pair": "tension-entropy",
          "from": "stable",
          "to": "decreasing"
        },
        {
          "pair": "tension-trust",
          "from": "increasing",
          "to": "stable"
        }
      ]
    },
    {
      "dimension": "exceedanceSeverity (beats)",
      "delta": 13.23,
      "tolerance": 35,
      "status": "stable",
      "currentTotal": 48,
      "previousTotal": 6,
      "currentUnique": 21,
      "previousUnique": 2,
      "currentTopPair": {
        "pair": "density-flicker",
        "beats": 21
      },
      "previousTopPair": {
        "pair": "density-flicker",
        "beats": 2
      },
      "normalizedDelta": true
    },
    {
      "dimension": "hotspotMigration",
      "delta": 0.1526,
      "tolerance": 0.55,
      "status": "stable",
      "currentTopPair": "density-flicker",
      "previousTopPair": "density-flicker",
      "currentTop2Concentration": 0.5833,
      "previousTop2Concentration": 0.5,
      "pairSetDelta": 0.5,
      "currentAxisShares": {
        "density": 0.1348,
        "tension": 0.1667,
        "flicker": 0.1612,
        "entropy": 0.2177,
        "trust": 0.171,
        "phase": 0.1486
      },
      "previousAxisShares": {
        "density": 0.2622,
        "tension": 0.1229,
        "flicker": 0.232,
        "entropy": 0.156,
        "trust": 0.2269,
        "phase": 0
      }
    },
    {
      "dimension": "telemetryHealth",
      "delta": 0.1409,
      "tolerance": 0.35,
      "status": "stable",
      "current": {
        "score": 0.3519,
        "phaseTelemetryPresent": true,
        "phaseIntegrity": "warning",
        "underSeenPairCount": 2,
        "maxGap": 0.195
      },
      "previous": {
        "score": 0.3728,
        "phaseTelemetryPresent": true,
        "phaseIntegrity": "critical",
        "underSeenPairCount": 0,
        "maxGap": 0
      }
    }
  ]
}